tracfieldtooltip/__init__.py
tracfieldtooltip/tooltip.py
tracfieldtooltip/htdocs/tooltip.css
tracfieldtooltip/htdocs/tooltip.js
TracFieldTooltip-0.8.6.dist-info/COPYING
TracFieldTooltip-0.8.6.dist-info/METADATA
TracFieldTooltip-0.8.6.dist-info/WHEEL
TracFieldTooltip-0.8.6.dist-info/entry_points.txt
TracFieldTooltip-0.8.6.dist-info/top_level.txt
TracFieldTooltip-0.8.6.dist-info/zip-safe
TracFieldTooltip-0.8.6.dist-info/RECORD
